deepseek_reverse/__init__.py
deepseek_reverse/_internal.py
deepseek_reverse/api.py
deepseek_reverse/sha3.wasm
deepseek_reverse-0.2.1.dist-info/METADATA
deepseek_reverse-0.2.1.dist-info/WHEEL
deepseek_reverse-0.2.1.dist-info/top_level.txt
deepseek_reverse-0.2.1.dist-info/RECORD
