Metadata-Version: 2.4
Name: deepseek_reverse
Version: 0.2.1
Summary: Add your description here
Requires-Python: >=3.12
Requires-Dist: curl-cffi>=0.10.0
Requires-Dist: jinja2>=3.1.6
Requires-Dist: wasmtime>=31.0.0
